quax/__init__.py
quax/_compat.py
quax/_core.py
quax/py.typed
quax/examples/README.md
quax/examples/__init__.py
quax/examples/lora/README.md
quax/examples/lora/__init__.py
quax/examples/lora/_core.py
quax/examples/named/README.md
quax/examples/named/__init__.py
quax/examples/named/_core.py
quax/examples/prng/README.md
quax/examples/prng/__init__.py
quax/examples/prng/_core.py
quax/examples/sparse/README.md
quax/examples/sparse/__init__.py
quax/examples/sparse/_core.py
quax/examples/structured_matrices/README.md
quax/examples/structured_matrices/__init__.py
quax/examples/structured_matrices/_core.py
quax/examples/unitful/__init__.py
quax/examples/unitful/_core.py
quax/examples/zero/README.md
quax/examples/zero/__init__.py
quax/examples/zero/_core.py
quax-0.2.1.dist-info/METADATA
quax-0.2.1.dist-info/WHEEL
quax-0.2.1.dist-info/licenses/LICENSE
quax-0.2.1.dist-info/RECORD
