Metadata-Version: 2.4
Name: quax
Version: 0.2.1
Summary: Multiple dispatch in JAX via custom interpreters.
Project-URL: repository, https://github.com/patrick-kidger/quax
Author-email: Patrick Kidger <contact@kidger.site>
License:                                  Apache License
License-File: LICENSE
Keywords: equinox,jax,multiple-dispatch
Classifier: Development Status :: 3 - Alpha
Classifier: Intended Audience :: Developers
Classifier: Intended Audience :: Financial and Insurance Industry
Classifier: Intended Audience :: Information Technology
Classifier: Intended Audience :: Science/Research
Classifier: License :: OSI Approved :: Apache Software License
Classifier: Natural Language :: English
Classifier: Programming Language :: Python :: 3
Classifier: Topic :: Scientific/Engineering :: Artificial Intelligence
Classifier: Topic :: Scientific/Engineering :: Information Analysis
Classifier: Topic :: Scientific/Engineering :: Mathematics
Requires-Python: >=3.10
Requires-Dist: equinox>=0.13.2
Requires-Dist: jax!=0.7.0,!=0.7.1,>=0.5.3
Requires-Dist: jaxtyping>=0.3.3
Requires-Dist: plum-dispatch>=2.2.1
Provides-Extra: dev
Requires-Dist: pre-commit>=4.1.0; extra == 'dev'
Provides-Extra: docs
Requires-Dist: hippogriffe==0.2.0; extra == 'docs'
Requires-Dist: mkdocs-include-exclude-files==0.1.0; extra == 'docs'
Requires-Dist: mkdocs-ipynb==0.1.1; extra == 'docs'
Requires-Dist: mkdocs-material==9.6.7; extra == 'docs'
Requires-Dist: mkdocs==1.6.1; extra == 'docs'
Requires-Dist: mkdocstrings[python]==0.28.3; extra == 'docs'
Requires-Dist: pymdown-extensions==10.14.3; extra == 'docs'
Provides-Extra: tests
Requires-Dist: beartype>=0.20.2; extra == 'tests'
Requires-Dist: jax[cpu]; extra == 'tests'
Requires-Dist: pytest-env>=1.1.5; extra == 'tests'
Requires-Dist: pytest>=8.3.5; extra == 'tests'
